django_nifty_layout-0.2.0.dist-info/licenses/LICENSE
nifty_layout/__init__.py
nifty_layout/accessor.py
nifty_layout/apps.py
nifty_layout/components.py
django_nifty_layout-0.2.0.dist-info/METADATA
django_nifty_layout-0.2.0.dist-info/WHEEL
django_nifty_layout-0.2.0.dist-info/entry_points.txt
django_nifty_layout-0.2.0.dist-info/top_level.txt
django_nifty_layout-0.2.0.dist-info/RECORD
